README.txt
setup.py
collective/__init__.py
collective.cu3er.egg-info/PKG-INFO
collective.cu3er.egg-info/SOURCES.txt
collective.cu3er.egg-info/dependency_links.txt
collective.cu3er.egg-info/entry_points.txt
collective.cu3er.egg-info/namespace_packages.txt
collective.cu3er.egg-info/not-zip-safe
collective.cu3er.egg-info/requires.txt
collective.cu3er.egg-info/top_level.txt
collective/cu3er/__init__.py
collective/cu3er/__init__.pyc
collective/cu3er/configure.zcml
collective/cu3er/interfaces.py
collective/cu3er/interfaces.pyc
collective/cu3er/schemaextender.py
collective/cu3er/setuphandlers.py
collective/cu3er/setuphandlers.pyc
collective/cu3er/tests.py
collective/cu3er/Extensions/Install.py
collective/cu3er/Extensions/__init__.py
collective/cu3er/browser/__init__.py
collective/cu3er/browser/configure.zcml
collective/cu3er/browser/viewlets.py
collective/cu3er/browser/views.py
collective/cu3er/browser/css/cu3er.css
collective/cu3er/browser/flash/cu3er.swf
collective/cu3er/browser/flash/expressInstall.swf
collective/cu3er/browser/images/slide_1.jpg
collective/cu3er/browser/images/slide_2.jpg
collective/cu3er/browser/images/slide_3.jpg
collective/cu3er/browser/images/slide_4.jpg
collective/cu3er/browser/images/slide_5.jpg
collective/cu3er/browser/javascript/cu3er.js
collective/cu3er/browser/javascript/swfobject.js
collective/cu3er/browser/templates/config.xml
collective/cu3er/browser/templates/cu3er.pt
collective/cu3er/profiles/default/browserlayer.xml
collective/cu3er/profiles/default/collective.cu3er.txt
collective/cu3er/profiles/default/cssregistry.xml
collective/cu3er/profiles/default/jsregistry.xml
collective/cu3er/profiles/default/metadata.xml
collective/cu3er/profiles/uninstall/collective.cu3er_uninstall.txt
collective/cu3er/profiles/uninstall/import_steps.xml
docs/HISTORY.txt
docs/INSTALL.txt
docs/LICENSE.GPL
docs/LICENSE.txt