Metadata-Version: 1.0
Name: collective.cu3er
Version: 0.1
Summary: CU3ER integration for Plone
Home-page: http://svn.plone.org/svn/collective/collective.cu3er
Author: Thomas Massmann
Author-email: thomas.massmann@inqbus.de
License: GPL
Keywords: Zope Plone JavaScrip Slideshow CU3ER Viewlet
Platform: UNKNOWN
Classifier: Framework :: Plone
Classifier: Programming Language :: Python
